django_elastic_filter/__init__.py
django_elastic_filter/dynamic.py
django_elastic_filter/elastic_filter.py
django_elastic_filter/sub_serializer.py
django_elastic_filter/utils.py
django_elastic_filter-1.0.17.dist-info/METADATA
django_elastic_filter-1.0.17.dist-info/WHEEL
django_elastic_filter-1.0.17.dist-info/top_level.txt
django_elastic_filter-1.0.17.dist-info/RECORD
